{
    "owner": "Badgerdox",
    "owner_type": "User",
    "homepage": "HomePage",
    "url": "https://github.com/Badgerdox/AddressableAsset-HowTo",
    "description": "",
    "name": "AddressableAsset-HowTo",
    "full_name": "Badgerdox/AddressableAsset-HowTo",
    "id": 222146948,
    "topics": [
        "unity",
        "addressable",
        "unity-addressables",
        "gamedev",
        "liveops"
    ],
    "lists": [
        "Useful Unity Stuff",
        "Educational Stuff"
    ],
    "license": {}
}