{
    "owner": "AlexStormwood",
    "owner_type": "User",
    "homepage": "https://nestednetlifygitdeployment.netlify.app/",
    "url": "https://github.com/AlexStormwood/NestedNetlifyDeploymentExample",
    "description": "",
    "name": "NestedNetlifyDeploymentExample",
    "full_name": "AlexStormwood/NestedNetlifyDeploymentExample",
    "id": 265456872,
    "topics": [
        "html",
        "css",
        "webdev"
    ],
    "lists": [
        "My Own Work",
        "Educational Stuff",
        "Useful Programming Concepts Stuff"
    ],
    "license": {}
}