{
    "owner": "joaorb64",
    "owner_type": "User",
    "homepage": "https://joaorb64.github.io/StreamHelperAssets/",
    "url": "https://github.com/joaorb64/StreamHelperAssets",
    "description": "Character assets for use with TournamentStreamHelper",
    "name": "StreamHelperAssets",
    "full_name": "joaorb64/StreamHelperAssets",
    "id": 390728416,
    "topics": [
        "streaming",
        "art",
        "game",
        "games",
        "gaming"
    ],
    "lists": [
        "Useful Streaming Stuff"
    ],
    "license": {}
}