{
    "owner": "AlexStormwood",
    "owner_type": "User",
    "homepage": "",
    "url": "https://github.com/AlexStormwood/jul24-t2w7-react-refresher",
    "description": "Front-end for the Express Refresher project.",
    "name": "jul24-t2w7-react-refresher",
    "full_name": "AlexStormwood/jul24-t2w7-react-refresher",
    "id": 940874656,
    "topics": [
        "react",
        "reactjs",
        "webdev",
        "javascript"
    ],
    "lists": [
        "CA - 2024-JUL-DWD"
    ],
    "license": {}
}